spotiphy/__init__.py
spotiphy/deconvolution.py
spotiphy/plot.py
spotiphy/sc_reference.py
spotiphy/segmentation.py
spotiphy/utils_visiumhd.py
spotiphy-0.3.1.dist-info/licenses/LICENSE
spotiphy-0.3.1.dist-info/METADATA
spotiphy-0.3.1.dist-info/WHEEL
spotiphy-0.3.1.dist-info/top_level.txt
spotiphy-0.3.1.dist-info/RECORD
