Metadata-Version: 2.4
Name: spotiphy
Version: 0.3.1
Summary: An integrated pipeline designed to deconvolute and decompose spatial transcriptomics data, and produce pseudo single-cell resolution images.
Home-page: https://github.com/jyyulab/Spotiphy
Author: Ziqian Zheng, Jiyuan Yang
Author-email: zzheng92@wisc.edu
License: Apache-2.0
Requires-Python: >=3.9
License-File: LICENSE
Requires-Dist: squidpy==1.6.1
Requires-Dist: scanpy==1.10.3
Requires-Dist: scikit-learn==1.6.1
Requires-Dist: scipy==1.13.1
Requires-Dist: pandas==2.3.2
Requires-Dist: numpy==1.26.4
Requires-Dist: matplotlib
Requires-Dist: seaborn
Requires-Dist: tqdm
Requires-Dist: charset-normalizer==3.4.3
Requires-Dist: stardist==0.9.1
Requires-Dist: pyro-ppl==1.9.1
Requires-Dist: opencv-python>=4.10
Requires-Dist: jupyter
Dynamic: author
Dynamic: author-email
Dynamic: description
Dynamic: description-content-type
Dynamic: home-page
Dynamic: license
Dynamic: license-file
Dynamic: requires-dist
Dynamic: requires-python
Dynamic: summary
